<?xml version="1.0" encoding="UTF-8"?>

<FLOW VERSION="3.0" CLEANUP="true">
  <COMMENT></COMMENT>

  <!-- nodes -->

<BRANCH TIMEOUT="" LABELEXPRESSIONS="true">
  <COMMENT></COMMENT>

  <!-- nodes -->

<INVOKE NAME="%$list% != $null and %$pattern% != $null and %$replacement% != $null" TIMEOUT="" SERVICE="tundra.list.string:map" VALIDATE-IN="$none" VALIDATE-OUT="$none">
  <COMMENT></COMMENT>

  <!-- nodes -->

<MAP MODE="INPUT">
  <MAPTARGET>

<Values version="2.0">
  <record name="xml" javaclass="com.wm.util.Values">
    <value name="node_type">record</value>
    <value name="is_public">false</value>
    <value name="field_type">record</value>
    <value name="field_dim">0</value>
    <value name="nillable">true</value>
    <value name="form_qualified">false</value>
    <value name="is_global">false</value>
    <array name="rec_fields" type="record" depth="1">
      <record javaclass="com.wm.util.Values">
        <value name="node_type">record</value>
        <value name="node_comment"></value>
        <record name="node_hints" javaclass="com.wm.util.Values">
          <value name="field_largerEditor">false</value>
          <value name="field_password">false</value>
        </record>
        <value name="is_public">false</value>
        <value name="field_name">$list</value>
        <value name="field_type">string</value>
        <value name="field_dim">1</value>
        <value name="field_opt">true</value>
        <record name="field_content_type" javaclass="com.wm.util.Values">
          <value name="contentType">1</value>
          <value name="internalType">reference</value>
          <value name="dataTypeVersion">dtVersion2</value>
          <array name="targetNames" type="record" depth="1">
            <record javaclass="com.wm.util.Values">
              <value name="xmlns">http://www.w3.org/2001/XMLSchema</value>
              <value name="ncName">string</value>
            </record>
          </array>
        </record>
        <value name="nillable">true</value>
        <value name="form_qualified">false</value>
        <value name="is_global">false</value>
        <value name="is_soap_array_encoding_used">false</value>
      </record>
      <record javaclass="com.wm.util.Values">
        <value name="node_type">record</value>
        <value name="node_comment"></value>
        <record name="node_hints" javaclass="com.wm.util.Values">
          <null name="field_usereditable"/>
          <value name="field_largerEditor">false</value>
          <value name="field_password">false</value>
        </record>
        <value name="is_public">false</value>
        <value name="field_name">$service</value>
        <value name="field_type">string</value>
        <value name="field_dim">0</value>
        <value name="field_opt">true</value>
        <record name="field_content_type" javaclass="com.wm.util.Values">
          <value name="contentType">1</value>
          <value name="internalType">reference</value>
          <value name="dataTypeVersion">dtVersion2</value>
          <array name="targetNames" type="record" depth="1">
            <record javaclass="com.wm.util.Values">
              <value name="xmlns">http://www.w3.org/2001/XMLSchema</value>
              <value name="ncName">string</value>
            </record>
          </array>
        </record>
        <value name="nillable">true</value>
        <value name="form_qualified">false</value>
        <value name="is_global">false</value>
      </record>
      <record javaclass="com.wm.util.Values">
        <value name="node_type">record</value>
        <value name="node_comment"></value>
        <record name="node_hints" javaclass="com.wm.util.Values">
          <value name="field_largerEditor">false</value>
          <value name="field_password">false</value>
        </record>
        <value name="is_public">false</value>
        <value name="field_name">$pipeline</value>
        <value name="field_type">record</value>
        <value name="field_dim">0</value>
        <value name="field_opt">true</value>
        <value name="nillable">true</value>
        <value name="form_qualified">false</value>
        <value name="is_global">false</value>
        <array name="rec_fields" type="record" depth="1">
          <record javaclass="com.wm.util.Values">
            <value name="node_type">unknown</value>
            <value name="is_public">false</value>
            <value name="field_name">$pattern</value>
            <value name="field_type">string</value>
            <value name="field_dim">0</value>
            <value name="nillable">true</value>
            <value name="form_qualified">false</value>
            <value name="is_global">false</value>
          </record>
          <record javaclass="com.wm.util.Values">
            <value name="node_type">unknown</value>
            <value name="is_public">false</value>
            <value name="field_name">$replacement</value>
            <value name="field_type">string</value>
            <value name="field_dim">0</value>
            <value name="nillable">true</value>
            <value name="form_qualified">false</value>
            <value name="is_global">false</value>
          </record>
          <record javaclass="com.wm.util.Values">
            <value name="node_type">unknown</value>
            <value name="is_public">false</value>
            <value name="field_name">$literal?</value>
            <value name="field_type">string</value>
            <value name="field_dim">0</value>
            <value name="nillable">true</value>
            <value name="form_qualified">false</value>
            <value name="is_global">false</value>
          </record>
          <record javaclass="com.wm.util.Values">
            <value name="node_type">unknown</value>
            <value name="is_public">false</value>
            <value name="field_name">$mode</value>
            <value name="field_type">string</value>
            <value name="field_dim">0</value>
            <value name="nillable">true</value>
            <value name="form_qualified">false</value>
            <value name="is_global">false</value>
          </record>
        </array>
        <value name="modifiable">true</value>
      </record>
      <record javaclass="com.wm.util.Values">
        <value name="node_type">record</value>
        <value name="node_comment"></value>
        <record name="node_hints" javaclass="com.wm.util.Values">
          <null name="field_usereditable"/>
          <value name="field_largerEditor">false</value>
          <value name="field_password">false</value>
        </record>
        <value name="is_public">false</value>
        <value name="field_name">$item.input</value>
        <value name="field_type">string</value>
        <value name="field_dim">0</value>
        <value name="field_opt">true</value>
        <record name="field_content_type" javaclass="com.wm.util.Values">
          <value name="contentType">1</value>
          <value name="internalType">reference</value>
          <value name="dataTypeVersion">dtVersion2</value>
          <array name="targetNames" type="record" depth="1">
            <record javaclass="com.wm.util.Values">
              <value name="xmlns">http://www.w3.org/2001/XMLSchema</value>
              <value name="ncName">string</value>
            </record>
          </array>
        </record>
        <value name="nillable">true</value>
        <value name="form_qualified">false</value>
        <value name="is_global">false</value>
      </record>
      <record javaclass="com.wm.util.Values">
        <value name="node_type">record</value>
        <value name="node_comment"></value>
        <record name="node_hints" javaclass="com.wm.util.Values">
          <null name="field_usereditable"/>
          <value name="field_largerEditor">false</value>
          <value name="field_password">false</value>
        </record>
        <value name="is_public">false</value>
        <value name="field_name">$item.output</value>
        <value name="field_type">string</value>
        <value name="field_dim">0</value>
        <value name="field_opt">true</value>
        <record name="field_content_type" javaclass="com.wm.util.Values">
          <value name="contentType">1</value>
          <value name="internalType">reference</value>
          <value name="dataTypeVersion">dtVersion2</value>
          <array name="targetNames" type="record" depth="1">
            <record javaclass="com.wm.util.Values">
              <value name="xmlns">http://www.w3.org/2001/XMLSchema</value>
              <value name="ncName">string</value>
            </record>
          </array>
        </record>
        <value name="nillable">true</value>
        <value name="form_qualified">false</value>
        <value name="is_global">false</value>
      </record>
    </array>
    <value name="modifiable">true</value>
  </record>
</Values>
</MAPTARGET>
  <MAPSOURCE>

<Values version="2.0">
  <record name="xml" javaclass="com.wm.util.Values">
    <value name="node_type">record</value>
    <value name="is_public">false</value>
    <value name="field_type">record</value>
    <value name="field_dim">0</value>
    <value name="nillable">true</value>
    <value name="form_qualified">false</value>
    <value name="is_global">false</value>
    <array name="rec_fields" type="record" depth="1">
      <record javaclass="com.wm.util.Values">
        <value name="node_type">record</value>
        <value name="node_comment"></value>
        <record name="node_hints" javaclass="com.wm.util.Values">
          <value name="field_largerEditor">false</value>
          <value name="field_password">false</value>
        </record>
        <value name="is_public">false</value>
        <value name="field_name">$list</value>
        <value name="field_type">string</value>
        <value name="field_dim">1</value>
        <value name="field_opt">true</value>
        <record name="field_content_type" javaclass="com.wm.util.Values">
          <value name="contentType">1</value>
          <value name="internalType">reference</value>
          <value name="dataTypeVersion">dtVersion2</value>
          <array name="targetNames" type="record" depth="1">
            <record javaclass="com.wm.util.Values">
              <value name="xmlns">http://www.w3.org/2001/XMLSchema</value>
              <value name="ncName">string</value>
            </record>
          </array>
        </record>
        <value name="nillable">true</value>
        <value name="form_qualified">false</value>
        <value name="is_global">false</value>
        <value name="is_soap_array_encoding_used">false</value>
      </record>
      <record javaclass="com.wm.util.Values">
        <value name="node_type">record</value>
        <value name="node_comment"></value>
        <record name="node_hints" javaclass="com.wm.util.Values">
          <null name="field_usereditable"/>
          <value name="field_largerEditor">false</value>
          <value name="field_password">false</value>
        </record>
        <value name="is_public">false</value>
        <value name="field_name">$pattern</value>
        <value name="field_type">string</value>
        <value name="field_dim">0</value>
        <value name="field_opt">true</value>
        <record name="field_content_type" javaclass="com.wm.util.Values">
          <value name="contentType">1</value>
          <value name="internalType">reference</value>
          <value name="dataTypeVersion">dtVersion2</value>
          <array name="targetNames" type="record" depth="1">
            <record javaclass="com.wm.util.Values">
              <value name="xmlns">http://www.w3.org/2001/XMLSchema</value>
              <value name="ncName">string</value>
            </record>
          </array>
        </record>
        <value name="nillable">true</value>
        <value name="form_qualified">false</value>
        <value name="is_global">false</value>
      </record>
      <record javaclass="com.wm.util.Values">
        <value name="node_type">record</value>
        <value name="node_comment"></value>
        <record name="node_hints" javaclass="com.wm.util.Values">
          <null name="field_usereditable"/>
          <value name="field_largerEditor">false</value>
          <value name="field_password">false</value>
        </record>
        <value name="is_public">false</value>
        <value name="field_name">$replacement</value>
        <value name="field_type">string</value>
        <value name="field_dim">0</value>
        <value name="field_opt">true</value>
        <record name="field_content_type" javaclass="com.wm.util.Values">
          <value name="contentType">1</value>
          <value name="internalType">reference</value>
          <value name="dataTypeVersion">dtVersion2</value>
          <array name="targetNames" type="record" depth="1">
            <record javaclass="com.wm.util.Values">
              <value name="xmlns">http://www.w3.org/2001/XMLSchema</value>
              <value name="ncName">string</value>
            </record>
          </array>
        </record>
        <value name="nillable">true</value>
        <value name="form_qualified">false</value>
        <value name="is_global">false</value>
      </record>
      <record javaclass="com.wm.util.Values">
        <value name="node_type">record</value>
        <value name="node_comment"></value>
        <record name="node_hints" javaclass="com.wm.util.Values">
          <value name="field_usereditable">false</value>
          <value name="field_largerEditor">false</value>
          <value name="field_password">false</value>
        </record>
        <value name="is_public">false</value>
        <value name="field_name">$literal?</value>
        <value name="field_type">string</value>
        <value name="field_dim">0</value>
        <value name="field_opt">true</value>
        <array name="field_options" type="value" depth="1">
          <value>false</value>
          <value>true</value>
        </array>
        <record name="field_content_type" javaclass="com.wm.util.Values">
          <value name="contentType">1</value>
          <value name="internalType">reference</value>
          <value name="dataTypeVersion">dtVersion2</value>
          <array name="targetNames" type="record" depth="1">
            <record javaclass="com.wm.util.Values">
              <value name="xmlns">http://www.w3.org/2001/XMLSchema</value>
              <value name="ncName">boolean</value>
            </record>
          </array>
        </record>
        <value name="nillable">true</value>
        <value name="form_qualified">false</value>
        <value name="is_global">false</value>
      </record>
      <record javaclass="com.wm.util.Values">
        <value name="node_type">record</value>
        <value name="node_comment"></value>
        <record name="node_hints" javaclass="com.wm.util.Values">
          <value name="field_usereditable">false</value>
          <value name="field_largerEditor">false</value>
          <value name="field_password">false</value>
        </record>
        <value name="is_public">false</value>
        <value name="field_name">$mode</value>
        <value name="field_type">string</value>
        <value name="field_dim">0</value>
        <value name="field_opt">true</value>
        <array name="field_options" type="value" depth="1">
          <value>all</value>
          <value>first</value>
        </array>
        <record name="field_content_type" javaclass="com.wm.util.Values">
          <array name="enumeration" type="record" depth="1">
            <record javaclass="com.wm.util.Values">
              <value name="primitiveType">0</value>
              <value name="lexRep">all</value>
              <value name="isList">false</value>
            </record>
            <record javaclass="com.wm.util.Values">
              <value name="primitiveType">0</value>
              <value name="lexRep">first</value>
              <value name="isList">false</value>
            </record>
          </array>
          <value name="contentType">1</value>
          <value name="internalType">instance</value>
          <value name="ct_class">com.wm.lang.schema.datatypev2.WmString</value>
          <value name="name">string_customized</value>
          <array name="parent-ancestors" type="record" depth="1">
            <record javaclass="com.wm.util.Values">
              <value name="xmlns">http://www.w3.org/2001/XMLSchema</value>
              <value name="ncName">anySimpleType</value>
            </record>
            <record javaclass="com.wm.util.Values">
              <value name="xmlns">http://www.w3.org/2001/XMLSchema</value>
              <value name="ncName">anyType</value>
            </record>
            <record javaclass="com.wm.util.Values">
              <value name="xmlns">http://www.w3.org/2001/XMLSchema</value>
              <value name="ncName">string</value>
            </record>
          </array>
          <record name="baseType" javaclass="com.wm.util.Values">
            <record name="whiteSpace" javaclass="com.wm.util.Values">
              <record name="FacetWSCValue" javaclass="com.wm.util.Values">
                <value name="cDecimalValue">3</value>
              </record>
              <value name="facetFixed">false</value>
            </record>
            <value name="contentType">1</value>
            <value name="internalType">instance</value>
            <value name="ct_class">com.wm.lang.schema.datatypev2.WmString</value>
            <value name="dataTypeVersion">dtVersion2</value>
          </record>
          <value name="dataTypeVersion">dtVersion2</value>
        </record>
        <value name="nillable">true</value>
        <value name="form_qualified">false</value>
        <value name="is_global">false</value>
      </record>
    </array>
    <value name="modifiable">true</value>
  </record>
</Values>
</MAPSOURCE>

  <!-- nodes -->

<MAPCOPY NAME="Link" FROM="/$pattern;1;0" TO="/$pipeline;2;0/$pattern;1;0">
</MAPCOPY>

<MAPCOPY NAME="Link" FROM="/$replacement;1;0" TO="/$pipeline;2;0/$replacement;1;0">
</MAPCOPY>

<MAPCOPY NAME="Link" FROM="/$literal?;1;0" TO="/$pipeline;2;0/$literal?;1;0">
</MAPCOPY>

<MAPDELETE NAME="Dropper" FIELD="/$pattern;1;0">
</MAPDELETE>

<MAPDELETE NAME="Dropper" FIELD="/$replacement;1;0">
</MAPDELETE>

<MAPDELETE NAME="Dropper" FIELD="/$literal?;1;0">
</MAPDELETE>

<MAPCOPY NAME="Link" FROM="/$mode;1;0" TO="/$pipeline;2;0/$mode;1;0">
</MAPCOPY>

<MAPDELETE NAME="Dropper" FIELD="/$mode;1;0">
</MAPDELETE>

<MAPSET NAME="Setter" OVERWRITE="true" VARIABLES="false" FIELD="/$item.output;1;0">
  <DATA ENCODING="XMLValues" I18N="true">

<Values version="2.0">
  <value name="xml">$string</value>
  <record name="type" javaclass="com.wm.util.Values">
    <value name="node_type">record</value>
    <value name="node_comment"></value>
    <record name="node_hints" javaclass="com.wm.util.Values">
      <null name="field_usereditable"/>
      <value name="field_largerEditor">false</value>
      <value name="field_password">false</value>
    </record>
    <value name="is_public">false</value>
    <value name="field_name">$item.output</value>
    <value name="field_type">string</value>
    <value name="field_dim">0</value>
    <value name="field_opt">true</value>
    <record name="field_content_type" javaclass="com.wm.util.Values">
      <value name="contentType">1</value>
      <value name="internalType">reference</value>
      <value name="dataTypeVersion">dtVersion2</value>
      <array name="targetNames" type="record" depth="1">
        <record javaclass="com.wm.util.Values">
          <value name="xmlns">http://www.w3.org/2001/XMLSchema</value>
          <value name="ncName">string</value>
        </record>
      </array>
    </record>
    <value name="nillable">true</value>
    <value name="form_qualified">false</value>
    <value name="is_global">false</value>
  </record>
</Values>
</DATA>
</MAPSET>

<MAPSET NAME="Setter" OVERWRITE="true" VARIABLES="false" FIELD="/$service;1;0">
  <DATA ENCODING="XMLValues" I18N="true">

<Values version="2.0">
  <value name="xml">tundra.string:replace</value>
  <record name="type" javaclass="com.wm.util.Values">
    <value name="node_type">record</value>
    <value name="node_comment"></value>
    <record name="node_hints" javaclass="com.wm.util.Values">
      <null name="field_usereditable"/>
      <value name="field_largerEditor">false</value>
      <value name="field_password">false</value>
    </record>
    <value name="is_public">false</value>
    <value name="field_name">$service</value>
    <value name="field_type">string</value>
    <value name="field_dim">0</value>
    <value name="field_opt">true</value>
    <record name="field_content_type" javaclass="com.wm.util.Values">
      <value name="contentType">1</value>
      <value name="internalType">reference</value>
      <value name="dataTypeVersion">dtVersion2</value>
      <array name="targetNames" type="record" depth="1">
        <record javaclass="com.wm.util.Values">
          <value name="xmlns">http://www.w3.org/2001/XMLSchema</value>
          <value name="ncName">string</value>
        </record>
      </array>
    </record>
    <value name="nillable">true</value>
    <value name="form_qualified">false</value>
    <value name="is_global">false</value>
  </record>
</Values>
</DATA>
</MAPSET>

<MAPSET NAME="Setter" OVERWRITE="true" VARIABLES="false" FIELD="/$item.input;1;0">
  <DATA ENCODING="XMLValues" I18N="true">

<Values version="2.0">
  <value name="xml">$string</value>
  <record name="type" javaclass="com.wm.util.Values">
    <value name="node_type">record</value>
    <value name="node_comment"></value>
    <record name="node_hints" javaclass="com.wm.util.Values">
      <null name="field_usereditable"/>
      <value name="field_largerEditor">false</value>
      <value name="field_password">false</value>
    </record>
    <value name="is_public">false</value>
    <value name="field_name">$item.input</value>
    <value name="field_type">string</value>
    <value name="field_dim">0</value>
    <value name="field_opt">true</value>
    <record name="field_content_type" javaclass="com.wm.util.Values">
      <value name="contentType">1</value>
      <value name="internalType">reference</value>
      <value name="dataTypeVersion">dtVersion2</value>
      <array name="targetNames" type="record" depth="1">
        <record javaclass="com.wm.util.Values">
          <value name="xmlns">http://www.w3.org/2001/XMLSchema</value>
          <value name="ncName">string</value>
        </record>
      </array>
    </record>
    <value name="nillable">true</value>
    <value name="form_qualified">false</value>
    <value name="is_global">false</value>
  </record>
</Values>
</DATA>
</MAPSET>
</MAP>

<MAP MODE="OUTPUT">
  <MAPTARGET>

<Values version="2.0">
  <record name="xml" javaclass="com.wm.util.Values">
    <value name="node_type">record</value>
    <value name="is_public">false</value>
    <value name="field_type">record</value>
    <value name="field_dim">0</value>
    <value name="nillable">true</value>
    <value name="form_qualified">false</value>
    <value name="is_global">false</value>
    <array name="rec_fields" type="record" depth="1">
      <record javaclass="com.wm.util.Values">
        <value name="node_type">record</value>
        <value name="node_comment"></value>
        <record name="node_hints" javaclass="com.wm.util.Values">
          <value name="field_largerEditor">false</value>
          <value name="field_password">false</value>
        </record>
        <value name="is_public">false</value>
        <value name="field_name">$list</value>
        <value name="field_type">string</value>
        <value name="field_dim">1</value>
        <value name="field_opt">true</value>
        <record name="field_content_type" javaclass="com.wm.util.Values">
          <value name="contentType">1</value>
          <value name="internalType">reference</value>
          <value name="dataTypeVersion">dtVersion2</value>
          <array name="targetNames" type="record" depth="1">
            <record javaclass="com.wm.util.Values">
              <value name="xmlns">http://www.w3.org/2001/XMLSchema</value>
              <value name="ncName">string</value>
            </record>
          </array>
        </record>
        <value name="nillable">true</value>
        <value name="form_qualified">false</value>
        <value name="is_global">false</value>
        <value name="is_soap_array_encoding_used">false</value>
      </record>
      <record javaclass="com.wm.util.Values">
        <value name="node_type">unknown</value>
        <value name="is_public">false</value>
        <value name="field_name">$service</value>
        <value name="field_type">string</value>
        <value name="field_dim">0</value>
        <value name="nillable">true</value>
        <value name="form_qualified">false</value>
        <value name="is_global">false</value>
      </record>
      <record javaclass="com.wm.util.Values">
        <value name="node_type">record</value>
        <value name="is_public">false</value>
        <value name="field_name">$pipeline</value>
        <value name="field_type">record</value>
        <value name="field_dim">0</value>
        <value name="nillable">true</value>
        <value name="form_qualified">false</value>
        <value name="is_global">false</value>
        <array name="rec_fields" type="record" depth="1">
          <record javaclass="com.wm.util.Values">
            <value name="node_type">unknown</value>
            <value name="is_public">false</value>
            <value name="field_name">$pattern</value>
            <value name="field_type">string</value>
            <value name="field_dim">0</value>
            <value name="nillable">true</value>
            <value name="form_qualified">false</value>
            <value name="is_global">false</value>
          </record>
          <record javaclass="com.wm.util.Values">
            <value name="node_type">unknown</value>
            <value name="is_public">false</value>
            <value name="field_name">$replacement</value>
            <value name="field_type">string</value>
            <value name="field_dim">0</value>
            <value name="nillable">true</value>
            <value name="form_qualified">false</value>
            <value name="is_global">false</value>
          </record>
          <record javaclass="com.wm.util.Values">
            <value name="node_type">unknown</value>
            <value name="is_public">false</value>
            <value name="field_name">$literal?</value>
            <value name="field_type">string</value>
            <value name="field_dim">0</value>
            <value name="nillable">true</value>
            <value name="form_qualified">false</value>
            <value name="is_global">false</value>
          </record>
          <record javaclass="com.wm.util.Values">
            <value name="node_type">unknown</value>
            <value name="is_public">false</value>
            <value name="field_name">$mode</value>
            <value name="field_type">string</value>
            <value name="field_dim">0</value>
            <value name="nillable">true</value>
            <value name="form_qualified">false</value>
            <value name="is_global">false</value>
          </record>
        </array>
        <value name="modifiable">true</value>
      </record>
      <record javaclass="com.wm.util.Values">
        <value name="node_type">unknown</value>
        <value name="is_public">false</value>
        <value name="field_name">$item.input</value>
        <value name="field_type">string</value>
        <value name="field_dim">0</value>
        <value name="nillable">true</value>
        <value name="form_qualified">false</value>
        <value name="is_global">false</value>
      </record>
      <record javaclass="com.wm.util.Values">
        <value name="node_type">unknown</value>
        <value name="is_public">false</value>
        <value name="field_name">$item.output</value>
        <value name="field_type">string</value>
        <value name="field_dim">0</value>
        <value name="nillable">true</value>
        <value name="form_qualified">false</value>
        <value name="is_global">false</value>
      </record>
    </array>
    <value name="modifiable">true</value>
  </record>
</Values>
</MAPTARGET>
  <MAPSOURCE>

<Values version="2.0">
  <record name="xml" javaclass="com.wm.util.Values">
    <value name="node_type">record</value>
    <value name="is_public">false</value>
    <value name="field_type">record</value>
    <value name="field_dim">0</value>
    <value name="nillable">true</value>
    <value name="form_qualified">false</value>
    <value name="is_global">false</value>
    <array name="rec_fields" type="record" depth="1">
    </array>
    <value name="modifiable">true</value>
  </record>
</Values>
</MAPSOURCE>

  <!-- nodes -->

<MAPDELETE NAME="Dropper" FIELD="/$service;1;0">
</MAPDELETE>

<MAPDELETE NAME="Dropper" FIELD="/$pipeline;2;0">
</MAPDELETE>

<MAPDELETE NAME="Dropper" FIELD="/$item.input;1;0">
</MAPDELETE>

<MAPDELETE NAME="Dropper" FIELD="/$item.output;1;0">
</MAPDELETE>
</MAP>
</INVOKE>
</BRANCH>
</FLOW>
